{
  "width": 176,
  "height": 236,
  "texture": "sapturretmod:textures/gui/tcu/page_info.png",
  "backgroundElements": [
    {
      "type": "texture",
      "data": {
        "size": [176, 236],
        "uv": [0, 0]
      }
    },
    {
      "type": "sapturretmod:turret_cam",
      "pos": [64, 30],
      "data": {
        "size": [48, 48],
        "quality": 512
      }
    },
    {
      "type": "sapturretmod:turret_name",
      "pos": [16, 9],
      "data": {
        "color": "0xFFA0A0FF"
      }
    },
    {
      "type": "textfield",
      "pos": [27, 87],
      "id": "turretNameInput",
      "data": {
        "size": [138, 10]
      }
    },
    {
      "type": "sapturretmod:tcu_info_playericon",
      "pos": [8, 148],
      "data": {
        "uvs": [
          [240,  0],
          [240, 16],
          [240, 32],
          [240, 48],
          [240, 64],
          [240, 80]
        ]
      }
    },
    {
      "type": "sapturretmod:tcu_info_progress",
      "pos": [6, 100],
      "data": {
        "type": "health",
        "bar": {
          "pos": [20, 11],
          "data": {
            "size": [140, 3],
            "uv": [116, 244]
          }
        },
        "text": {
          "pos": [20, 2],
          "data": {
            "color": "0xFFC20000"
          }
        }
      }
    },
    {
      "type": "sapturretmod:tcu_info_progress",
      "pos": [6, 100],
      "data": {
        "type": "personal_shield",
        "bar": {
          "pos": [20, 11],
          "data": {
            "size": [140, 3],
            "uv": [116, 250]
          }
        },
        "text": {
          "pos": [161, 2],
          "data": {
            "color": "0xFFC709DD",
            "justifyRight": true
          }
        }
      }
    },
    {
      "type": "sapturretmod:tcu_info_progress",
      "pos": [6, 116],
      "data": {
        "type": "ammo",
        "bar": {
          "pos": [20, 11],
          "data": {
            "size": [120, 3],
            "uv": [116, 247]
          }
        },
        "text": {
          "pos": [20, 2],
          "data": {
            "color": "0xFF0061C2"
          }
        }
      }
    },
    {
      "type": "sapturretmod:tcu_info_progress",
      "pos": [6, 132],
      "data": {
        "type": "target",
        "text": {
          "pos": [20, 4]
        }
      }
    },
    {
      "type": "sapturretmod:tcu_info_progress",
      "pos": [6, 148],
      "data": {
        "type": "player",
        "text": {
          "pos": [20, 4]
        }
      }
    },
    {
      "type": "sapturretmod:tcu_info_progress",
      "pos": [6, 164],
      "data": {
        "type": "forcefield",
        "bar": {
          "pos": [20, 11],
          "data": {
            "size": [140, 3],
            "uv": [116, 253],
            "uvBackground": [116, 236]
          }
        },
        "text": {
          "pos": [20, 2],
          "data": {
            "color": "0xFF997E00"
          }
        },
        "icon": {
          "type": "texture",
          "pos": [3, 0],
          "data": {
            "size": [16, 16],
            "uv": [176, 72]
          }
        }
      }
    },
    {
      "type": "button",
      "pos": [59, 186],
      "id": "dismantle",
      "data": {
        "size": [18, 18],
        "uvSize": [18, 18],
        "buttonFunction": 0,
        "texture": "sapturretmod:textures/gui/tcu/page_info.png",
        "uvEnabled": [176, 0]
      }
    },
    {
      "type": "button",
      "pos": [79, 186],
      "id": "activate",
      "data": {
        "size": [18, 18],
        "uvSize": [18, 18],
        "buttonFunction": 1,
        "texture": "sapturretmod:textures/gui/tcu/page_info.png",
        "uvEnabled": [194, 0]
      }
    },
    {
      "type": "button",
      "pos": [79, 186],
      "id": "deactivate",
      "data": {
        "size": [18, 18],
        "uvSize": [18, 18],
        "buttonFunction": 2,
        "texture": "sapturretmod:textures/gui/tcu/page_info.png",
        "uvEnabled": [212, 0]
      }
    },
    {
      "type": "button",
      "pos": [99, 186],
      "id": "showRange",
      "data": {
        "size": [18, 18],
        "uvSize": [18, 18],
        "buttonFunction": 3,
        "texture": "sapturretmod:textures/gui/tcu/page_info.png",
        "uvEnabled": [176, 36]
      }
    },
    {
      "type": "button",
      "pos": [99, 186],
      "id": "hideRange",
      "data": {
        "size": [18, 18],
        "uvSize": [18, 18],
        "buttonFunction": 4,
        "texture": "sapturretmod:textures/gui/tcu/page_info.png",
        "uvEnabled": [194, 36]
      }
    },
    {
      "type": "sapturretmod:tcu_info_ammo",
      "pos": [150, 116]
    },
    {
      "type": "sapturretmod:tcu_page_nav",
      "pos": [0, 214],
      "id": "pgNavigation",
      "data": {
        "tabScrollLeft": {
          "size": [16, 16],
          "uvSize": [16, 16],
          "uvEnabled": [18, 0]
        },
        "tabScrollRight": {
          "size": [16, 16],
          "uvSize": [16, 16],
          "uvEnabled": [36, 0]
        }
      }
    }
  ],
  "foregroundElements": [
    {
      "type": "button_label",
      "pos": [59, 186],
      "data": {
        "buttonId": "dismantle",
        "text": "gui.sapturretmod.tcu.button.dismantle"
      }
    },
    {
      "type": "button_label",
      "pos": [79, 186],
      "data": {
        "buttonId": "activate",
        "text": "gui.sapturretmod.tcu.button.activate"
      }
    },
    {
      "type": "button_label",
      "pos": [79, 186],
      "data": {
        "buttonId": "deactivate",
        "text": "gui.sapturretmod.tcu.button.deactivate"
      }
    },
    {
      "type": "button_label",
      "pos": [99, 186],
      "data": {
        "buttonId": "showRange",
        "text": "gui.sapturretmod.tcu.button.show_range"
      }
    },
    {
      "type": "button_label",
      "pos": [99, 186],
      "data": {
        "buttonId": "hideRange",
        "text": "gui.sapturretmod.tcu.button.hide_range"
      }
    },
    {
      "type": "sapturretmod:tcu_info_ammolabel",
      "pos": [150, 116]
    },
    {
      "type": "sapturretmod:tcu_page_nav_label",
      "pos": [0, 214],
      "data": {
        "for": "pgNavigation"
      }
    }
  ]
}